{"page":36,"lines":[{"lineNumber":1,"words":[{"code":"ﱁ","end":false},{"code":"ﱂ","end":false},{"code":"ﱃ","end":false},{"code":"ﱄ","end":false},{"code":"ﱅ","end":false},{"code":"ﱆ","end":false},{"code":"ﱇ","end":false},{"code":"ﱈ","end":false},{"code":"ﱉ","end":false},{"code":"ﱊ","end":false}]},{"lineNumber":2,"words":[{"code":"ﱋﱌ","end":false},{"code":"ﱍ","end":false},{"code":"ﱎ","end":false},{"code":"ﱏ","end":false},{"code":"ﱐ","end":true},{"code":"ﱑ","end":false},{"code":"ﱒ","end":false},{"code":"ﱓ","end":false},{"code":"ﱔ","end":false},{"code":"ﱕ","end":false}]},{"lineNumber":3,"words":[{"code":"ﱖ","end":false},{"code":"ﱗﱘ","end":false},{"code":"ﱙ","end":false},{"code":"ﱚ","end":false},{"code":"ﱛ","end":false},{"code":"ﱜ","end":false},{"code":"ﱝ","end":false},{"code":"ﱞ","end":false},{"code":"ﱟ","end":true},{"code":"ﱠ","end":false},{"code":"ﱡ","end":false}]},{"lineNumber":4,"words":[{"code":"ﱢ","end":false},{"code":"ﱣ","end":false},{"code":"ﱤ","end":false},{"code":"ﱥ","end":false},{"code":"ﱦ","end":false},{"code":"ﱧ","end":true},{"code":"ﱨ","end":false},{"code":"ﱩ","end":false},{"code":"ﱪ","end":false}]},{"lineNumber":5,"words":[{"code":"ﱫ","end":false},{"code":"ﱬﱭ","end":false},{"code":"ﱮ","end":false},{"code":"ﱯ","end":false},{"code":"ﱰ","end":false},{"code":"ﱱ","end":false},{"code":"ﱲ","end":false},{"code":"ﱳ","end":false},{"code":"ﱴ","end":false},{"code":"ﱵ","end":false},{"code":"ﱶ","end":false},{"code":"ﱷ","end":false}]},{"lineNumber":6,"words":[{"code":"ﱸ","end":false},{"code":"ﱹ","end":false},{"code":"ﱺ","end":false},{"code":"ﱻ","end":false},{"code":"ﱼ","end":false},{"code":"ﱽﱾ","end":false},{"code":"ﱿ","end":false},{"code":"ﲀ","end":false},{"code":"ﲁ","end":false},{"code":"ﲂ","end":false}]},{"lineNumber":7,"words":[{"code":"ﲃ","end":false},{"code":"ﲄ","end":false},{"code":"ﲅ","end":false},{"code":"ﲆﲇ","end":false},{"code":"ﲈ","end":false},{"code":"ﲉ","end":false},{"code":"ﲊ","end":false},{"code":"ﲋ","end":false},{"code":"ﲌﲍ","end":false}]},{"lineNumber":8,"words":[{"code":"ﲎ","end":false},{"code":"ﲏ","end":false},{"code":"ﲐﲑ","end":false},{"code":"ﲒ","end":false},{"code":"ﲓ","end":false},{"code":"ﲔ","end":false},{"code":"ﲕ","end":true},{"code":"ﲖ","end":false},{"code":"ﲗﲘ","end":false}]},{"lineNumber":9,"words":[{"code":"ﲙ","end":false},{"code":"ﲚ","end":false},{"code":"ﲛ","end":false},{"code":"ﲜ","end":false},{"code":"ﲝﲞ","end":false},{"code":"ﲟ","end":false},{"code":"ﲠ","end":false},{"code":"ﲡ","end":false},{"code":"ﲢ","end":false},{"code":"ﲣ","end":false}]},{"lineNumber":10,"words":[{"code":"ﲤ","end":false},{"code":"ﲥ","end":false},{"code":"ﲦ","end":false},{"code":"ﲧ","end":false},{"code":"ﲨ","end":false},{"code":"ﲩ","end":false},{"code":"ﲪ","end":false},{"code":"ﲫ","end":false},{"code":"ﲬ","end":false},{"code":"ﲭﲮ","end":false}]},{"lineNumber":11,"words":[{"code":"ﲯ","end":false},{"code":"ﲰ","end":false},{"code":"ﲱ","end":false},{"code":"ﲲ","end":false},{"code":"ﲳ","end":false},{"code":"ﲴ","end":false},{"code":"ﲵ","end":false},{"code":"ﲶ","end":false},{"code":"ﲷ","end":false},{"code":"ﲸ","end":false},{"code":"ﲹ","end":false}]},{"lineNumber":12,"words":[{"code":"ﲺﲻ","end":false},{"code":"ﲼ","end":false},{"code":"ﲽ","end":false},{"code":"ﲾ","end":false},{"code":"ﲿ","end":false},{"code":"ﳀﳁ","end":false},{"code":"ﳂ","end":false},{"code":"ﳃ","end":false},{"code":"ﳄ","end":false},{"code":"ﳅ","end":false},{"code":"ﳆ","end":false}]},{"lineNumber":13,"words":[{"code":"ﳇ","end":false},{"code":"ﳈ","end":false},{"code":"ﳉ","end":true},{"code":"ﳊ","end":false},{"code":"ﳋ","end":false},{"code":"ﳌ","end":false},{"code":"ﳍ","end":false},{"code":"ﳎ","end":false},{"code":"ﳏ","end":false},{"code":"ﳐ","end":false},{"code":"ﳑ","end":false},{"code":"ﳒ","end":false},{"code":"ﳓ","end":false}]},{"lineNumber":14,"words":[{"code":"ﳔﳕ","end":false},{"code":"ﳖ","end":false},{"code":"ﳗ","end":false},{"code":"ﳘ","end":false},{"code":"ﳙ","end":false},{"code":"ﳚ","end":false},{"code":"ﳛ","end":false},{"code":"ﳜ","end":false},{"code":"ﳝ","end":false},{"code":"ﳞ","end":false},{"code":"ﳟ","end":false}]},{"lineNumber":15,"words":[{"code":"ﳠ","end":false},{"code":"ﳡ","end":false},{"code":"ﳢﳣ","end":false},{"code":"ﳤ","end":false},{"code":"ﳥ","end":false},{"code":"ﳦ","end":false},{"code":"ﳧ","end":false},{"code":"ﳨ","end":false},{"code":"ﳩ","end":false},{"code":"ﳪ","end":true}]}],"verses":[{"key":"2:225","surah":2,"ayah":225,"num":232,"page":36,"words":[{"code":"ﱁ","page":36,"end":false},{"code":"ﱂ","page":36,"end":false},{"code":"ﱃ","page":36,"end":false},{"code":"ﱄ","page":36,"end":false},{"code":"ﱅ","page":36,"end":false},{"code":"ﱆ","page":36,"end":false},{"code":"ﱇ","page":36,"end":false},{"code":"ﱈ","page":36,"end":false},{"code":"ﱉ","page":36,"end":false},{"code":"ﱊ","page":36,"end":false},{"code":"ﱋﱌ","page":36,"end":false},{"code":"ﱍ","page":36,"end":false},{"code":"ﱎ","page":36,"end":false},{"code":"ﱏ","page":36,"end":false},{"code":"ﱐ","page":36,"end":true}],"text":"لَّا يُؤَاخِذُكُمُ ٱللَّهُ بِٱللَّغْوِ فِىٓ أَيْمَـٰنِكُمْ وَلَـٰكِن يُؤَاخِذُكُم بِمَا كَسَبَتْ قُلُوبُكُمْ ۗ وَٱللَّهُ غَفُورٌ حَلِيمٌۭ"},{"key":"2:226","surah":2,"ayah":226,"num":233,"page":36,"words":[{"code":"ﱑ","page":36,"end":false},{"code":"ﱒ","page":36,"end":false},{"code":"ﱓ","page":36,"end":false},{"code":"ﱔ","page":36,"end":false},{"code":"ﱕ","page":36,"end":false},{"code":"ﱖ","page":36,"end":false},{"code":"ﱗﱘ","page":36,"end":false},{"code":"ﱙ","page":36,"end":false},{"code":"ﱚ","page":36,"end":false},{"code":"ﱛ","page":36,"end":false},{"code":"ﱜ","page":36,"end":false},{"code":"ﱝ","page":36,"end":false},{"code":"ﱞ","page":36,"end":false},{"code":"ﱟ","page":36,"end":true}],"text":"لِّلَّذِينَ يُؤْلُونَ مِن نِّسَآئِهِمْ تَرَبُّصُ أَرْبَعَةِ أَشْهُرٍۢ ۖ فَإِن فَآءُو فَإِنَّ ٱللَّهَ غَفُورٌۭ رَّحِيمٌۭ"},{"key":"2:227","surah":2,"ayah":227,"num":234,"page":36,"words":[{"code":"ﱠ","page":36,"end":false},{"code":"ﱡ","page":36,"end":false},{"code":"ﱢ","page":36,"end":false},{"code":"ﱣ","page":36,"end":false},{"code":"ﱤ","page":36,"end":false},{"code":"ﱥ","page":36,"end":false},{"code":"ﱦ","page":36,"end":false},{"code":"ﱧ","page":36,"end":true}],"text":"وَإِنْ عَزَمُوا۟ ٱلطَّلَـٰقَ فَإِنَّ ٱللَّهَ سَمِيعٌ عَلِيمٌۭ"},{"key":"2:228","surah":2,"ayah":228,"num":235,"page":36,"words":[{"code":"ﱨ","page":36,"end":false},{"code":"ﱩ","page":36,"end":false},{"code":"ﱪ","page":36,"end":false},{"code":"ﱫ","page":36,"end":false},{"code":"ﱬﱭ","page":36,"end":false},{"code":"ﱮ","page":36,"end":false},{"code":"ﱯ","page":36,"end":false},{"code":"ﱰ","page":36,"end":false},{"code":"ﱱ","page":36,"end":false},{"code":"ﱲ","page":36,"end":false},{"code":"ﱳ","page":36,"end":false},{"code":"ﱴ","page":36,"end":false},{"code":"ﱵ","page":36,"end":false},{"code":"ﱶ","page":36,"end":false},{"code":"ﱷ","page":36,"end":false},{"code":"ﱸ","page":36,"end":false},{"code":"ﱹ","page":36,"end":false},{"code":"ﱺ","page":36,"end":false},{"code":"ﱻ","page":36,"end":false},{"code":"ﱼ","page":36,"end":false},{"code":"ﱽﱾ","page":36,"end":false},{"code":"ﱿ","page":36,"end":false},{"code":"ﲀ","page":36,"end":false},{"code":"ﲁ","page":36,"end":false},{"code":"ﲂ","page":36,"end":false},{"code":"ﲃ","page":36,"end":false},{"code":"ﲄ","page":36,"end":false},{"code":"ﲅ","page":36,"end":false},{"code":"ﲆﲇ","page":36,"end":false},{"code":"ﲈ","page":36,"end":false},{"code":"ﲉ","page":36,"end":false},{"code":"ﲊ","page":36,"end":false},{"code":"ﲋ","page":36,"end":false},{"code":"ﲌﲍ","page":36,"end":false},{"code":"ﲎ","page":36,"end":false},{"code":"ﲏ","page":36,"end":false},{"code":"ﲐﲑ","page":36,"end":false},{"code":"ﲒ","page":36,"end":false},{"code":"ﲓ","page":36,"end":false},{"code":"ﲔ","page":36,"end":false},{"code":"ﲕ","page":36,"end":true}],"text":"وَٱلْمُطَلَّقَـٰتُ يَتَرَبَّصْنَ بِأَنفُسِهِنَّ ثَلَـٰثَةَ قُرُوٓءٍۢ ۚ وَلَا يَحِلُّ لَهُنَّ أَن يَكْتُمْنَ مَا خَلَقَ ٱللَّهُ فِىٓ أَرْحَامِهِنَّ إِن كُنَّ يُؤْمِنَّ بِٱللَّهِ وَٱلْيَوْمِ ٱلْـَٔاخِرِ ۚ وَبُعُولَتُهُنَّ أَحَقُّ بِرَدِّهِنَّ فِى ذَٰلِكَ إِنْ أَرَادُوٓا۟ إِصْلَـٰحًۭا ۚ وَلَهُنَّ مِثْلُ ٱلَّذِى عَلَيْهِنَّ بِٱلْمَعْرُوفِ ۚ وَلِلرِّجَالِ عَلَيْهِنَّ دَرَجَةٌۭ ۗ وَٱللَّهُ عَزِيزٌ حَكِيمٌ"},{"key":"2:229","surah":2,"ayah":229,"num":236,"page":36,"words":[{"code":"ﲖ","page":36,"end":false},{"code":"ﲗﲘ","page":36,"end":false},{"code":"ﲙ","page":36,"end":false},{"code":"ﲚ","page":36,"end":false},{"code":"ﲛ","page":36,"end":false},{"code":"ﲜ","page":36,"end":false},{"code":"ﲝﲞ","page":36,"end":false},{"code":"ﲟ","page":36,"end":false},{"code":"ﲠ","page":36,"end":false},{"code":"ﲡ","page":36,"end":false},{"code":"ﲢ","page":36,"end":false},{"code":"ﲣ","page":36,"end":false},{"code":"ﲤ","page":36,"end":false},{"code":"ﲥ","page":36,"end":false},{"code":"ﲦ","page":36,"end":false},{"code":"ﲧ","page":36,"end":false},{"code":"ﲨ","page":36,"end":false},{"code":"ﲩ","page":36,"end":false},{"code":"ﲪ","page":36,"end":false},{"code":"ﲫ","page":36,"end":false},{"code":"ﲬ","page":36,"end":false},{"code":"ﲭﲮ","page":36,"end":false},{"code":"ﲯ","page":36,"end":false},{"code":"ﲰ","page":36,"end":false},{"code":"ﲱ","page":36,"end":false},{"code":"ﲲ","page":36,"end":false},{"code":"ﲳ","page":36,"end":false},{"code":"ﲴ","page":36,"end":false},{"code":"ﲵ","page":36,"end":false},{"code":"ﲶ","page":36,"end":false},{"code":"ﲷ","page":36,"end":false},{"code":"ﲸ","page":36,"end":false},{"code":"ﲹ","page":36,"end":false},{"code":"ﲺﲻ","page":36,"end":false},{"code":"ﲼ","page":36,"end":false},{"code":"ﲽ","page":36,"end":false},{"code":"ﲾ","page":36,"end":false},{"code":"ﲿ","page":36,"end":false},{"code":"ﳀﳁ","page":36,"end":false},{"code":"ﳂ","page":36,"end":false},{"code":"ﳃ","page":36,"end":false},{"code":"ﳄ","page":36,"end":false},{"code":"ﳅ","page":36,"end":false},{"code":"ﳆ","page":36,"end":false},{"code":"ﳇ","page":36,"end":false},{"code":"ﳈ","page":36,"end":false},{"code":"ﳉ","page":36,"end":true}],"text":"ٱلطَّلَـٰقُ مَرَّتَانِ ۖ فَإِمْسَاكٌۢ بِمَعْرُوفٍ أَوْ تَسْرِيحٌۢ بِإِحْسَـٰنٍۢ ۗ وَلَا يَحِلُّ لَكُمْ أَن تَأْخُذُوا۟ مِمَّآ ءَاتَيْتُمُوهُنَّ شَيْـًٔا إِلَّآ أَن يَخَافَآ أَلَّا يُقِيمَا حُدُودَ ٱللَّهِ ۖ فَإِنْ خِفْتُمْ أَلَّا يُقِيمَا حُدُودَ ٱللَّهِ فَلَا جُنَاحَ عَلَيْهِمَا فِيمَا ٱفْتَدَتْ بِهِۦ ۗ تِلْكَ حُدُودُ ٱللَّهِ فَلَا تَعْتَدُوهَا ۚ وَمَن يَتَعَدَّ حُدُودَ ٱللَّهِ فَأُو۟لَـٰٓئِكَ هُمُ ٱلظَّـٰلِمُونَ"},{"key":"2:230","surah":2,"ayah":230,"num":237,"page":36,"words":[{"code":"ﳊ","page":36,"end":false},{"code":"ﳋ","page":36,"end":false},{"code":"ﳌ","page":36,"end":false},{"code":"ﳍ","page":36,"end":false},{"code":"ﳎ","page":36,"end":false},{"code":"ﳏ","page":36,"end":false},{"code":"ﳐ","page":36,"end":false},{"code":"ﳑ","page":36,"end":false},{"code":"ﳒ","page":36,"end":false},{"code":"ﳓ","page":36,"end":false},{"code":"ﳔﳕ","page":36,"end":false},{"code":"ﳖ","page":36,"end":false},{"code":"ﳗ","page":36,"end":false},{"code":"ﳘ","page":36,"end":false},{"code":"ﳙ","page":36,"end":false},{"code":"ﳚ","page":36,"end":false},{"code":"ﳛ","page":36,"end":false},{"code":"ﳜ","page":36,"end":false},{"code":"ﳝ","page":36,"end":false},{"code":"ﳞ","page":36,"end":false},{"code":"ﳟ","page":36,"end":false},{"code":"ﳠ","page":36,"end":false},{"code":"ﳡ","page":36,"end":false},{"code":"ﳢﳣ","page":36,"end":false},{"code":"ﳤ","page":36,"end":false},{"code":"ﳥ","page":36,"end":false},{"code":"ﳦ","page":36,"end":false},{"code":"ﳧ","page":36,"end":false},{"code":"ﳨ","page":36,"end":false},{"code":"ﳩ","page":36,"end":false},{"code":"ﳪ","page":36,"end":true}],"text":"فَإِن طَلَّقَهَا فَلَا تَحِلُّ لَهُۥ مِنۢ بَعْدُ حَتَّىٰ تَنكِحَ زَوْجًا غَيْرَهُۥ ۗ فَإِن طَلَّقَهَا فَلَا جُنَاحَ عَلَيْهِمَآ أَن يَتَرَاجَعَآ إِن ظَنَّآ أَن يُقِيمَا حُدُودَ ٱللَّهِ ۗ وَتِلْكَ حُدُودُ ٱللَّهِ يُبَيِّنُهَا لِقَوْمٍۢ يَعْلَمُونَ"}]}