{"page":499,"lines":[{"lineNumber":2,"words":[{"code":"ﱁ","end":false},{"code":"ﱂ","end":true},{"code":"ﱃ","end":false},{"code":"ﱄ","end":false},{"code":"ﱅ","end":false},{"code":"ﱆ","end":false},{"code":"ﱇ","end":false},{"code":"ﱈ","end":false},{"code":"ﱉ","end":true},{"code":"ﱊ","end":false},{"code":"ﱋ","end":false},{"code":"ﱌ","end":false}]},{"lineNumber":3,"words":[{"code":"ﱍ","end":false},{"code":"ﱎ","end":false},{"code":"ﱏ","end":false},{"code":"ﱐ","end":true},{"code":"ﱑ","end":false},{"code":"ﱒ","end":false},{"code":"ﱓ","end":false},{"code":"ﱔ","end":false},{"code":"ﱕ","end":false},{"code":"ﱖ","end":false},{"code":"ﱗ","end":false}]},{"lineNumber":4,"words":[{"code":"ﱘ","end":false},{"code":"ﱙ","end":false},{"code":"ﱚ","end":true},{"code":"ﱛ","end":false},{"code":"ﱜ","end":false},{"code":"ﱝ","end":false},{"code":"ﱞ","end":false},{"code":"ﱟ","end":false},{"code":"ﱠ","end":false},{"code":"ﱡ","end":false},{"code":"ﱢ","end":false}]},{"lineNumber":5,"words":[{"code":"ﱣ","end":false},{"code":"ﱤ","end":false},{"code":"ﱥ","end":false},{"code":"ﱦ","end":false},{"code":"ﱧ","end":false},{"code":"ﱨ","end":false},{"code":"ﱩ","end":false},{"code":"ﱪ","end":false},{"code":"ﱫ","end":false},{"code":"ﱬ","end":false},{"code":"ﱭ","end":false}]},{"lineNumber":6,"words":[{"code":"ﱮ","end":false},{"code":"ﱯ","end":true},{"code":"ﱰ","end":false},{"code":"ﱱ","end":false},{"code":"ﱲ","end":false},{"code":"ﱳ","end":false},{"code":"ﱴ","end":false},{"code":"ﱵﱶ","end":false},{"code":"ﱷ","end":false},{"code":"ﱸ","end":false},{"code":"ﱹ","end":false}]},{"lineNumber":7,"words":[{"code":"ﱺ","end":false},{"code":"ﱻ","end":false},{"code":"ﱼ","end":false},{"code":"ﱽ","end":true},{"code":"ﱾ","end":false},{"code":"ﱿ","end":false},{"code":"ﲀ","end":false},{"code":"ﲁ","end":false},{"code":"ﲂ","end":true},{"code":"ﲃ","end":false},{"code":"ﲄ","end":false}]},{"lineNumber":8,"words":[{"code":"ﲅ","end":false},{"code":"ﲆ","end":false},{"code":"ﲇ","end":false},{"code":"ﲈ","end":false},{"code":"ﲉ","end":false},{"code":"ﲊ","end":false},{"code":"ﲋ","end":false},{"code":"ﲌ","end":false},{"code":"ﲍﲎ","end":false},{"code":"ﲏ","end":false},{"code":"ﲐ","end":false},{"code":"ﲑ","end":false}]},{"lineNumber":9,"words":[{"code":"ﲒ","end":true},{"code":"ﲓ","end":false},{"code":"ﲔ","end":false},{"code":"ﲕ","end":false},{"code":"ﲖ","end":false},{"code":"ﲗ","end":false},{"code":"ﲘ","end":false},{"code":"ﲙﲚ","end":false},{"code":"ﲛ","end":false},{"code":"ﲜ","end":false},{"code":"ﲝ","end":false}]},{"lineNumber":10,"words":[{"code":"ﲞ","end":false},{"code":"ﲟ","end":true},{"code":"ﲠ","end":false},{"code":"ﲡ","end":false},{"code":"ﲢﲣ","end":false},{"code":"ﲤ","end":false},{"code":"ﲥ","end":false},{"code":"ﲦ","end":false},{"code":"ﲧ","end":false},{"code":"ﲨ","end":false},{"code":"ﲩ","end":false}]},{"lineNumber":11,"words":[{"code":"ﲪ","end":false},{"code":"ﲫ","end":false},{"code":"ﲬ","end":false},{"code":"ﲭ","end":false},{"code":"ﲮ","end":false},{"code":"ﲯ","end":false},{"code":"ﲰﲱ","end":false},{"code":"ﲲ","end":false},{"code":"ﲳ","end":false},{"code":"ﲴ","end":false},{"code":"ﲵ","end":true},{"code":"ﲶ","end":false}]},{"lineNumber":12,"words":[{"code":"ﲷﲸ","end":false},{"code":"ﲹ","end":false},{"code":"ﲺ","end":false},{"code":"ﲻ","end":false},{"code":"ﲼ","end":false},{"code":"ﲽ","end":false},{"code":"ﲾ","end":false},{"code":"ﲿ","end":false},{"code":"ﳀ","end":false},{"code":"ﳁ","end":false},{"code":"ﳂ","end":true}]},{"lineNumber":13,"words":[{"code":"ﳃ ﳄ","end":false},{"code":"ﳅ","end":false},{"code":"ﳆ","end":false},{"code":"ﳇ","end":false},{"code":"ﳈ","end":false},{"code":"ﳉ","end":false},{"code":"ﳊ","end":false},{"code":"ﳋ","end":false},{"code":"ﳌ","end":false},{"code":"ﳍ","end":false}]},{"lineNumber":14,"words":[{"code":"ﳎ","end":false},{"code":"ﳏ","end":false},{"code":"ﳐ","end":false},{"code":"ﳑ","end":false},{"code":"ﳒ","end":true},{"code":"ﳓ","end":false},{"code":"ﳔ","end":false},{"code":"ﳕ","end":false},{"code":"ﳖ","end":false},{"code":"ﳗ","end":false},{"code":"ﳘ","end":false},{"code":"ﳙ","end":false}]},{"lineNumber":15,"words":[{"code":"ﳚ","end":false},{"code":"ﳛ","end":false},{"code":"ﳜﳝ","end":false},{"code":"ﳞ","end":false},{"code":"ﳟ","end":false},{"code":"ﳠ","end":false},{"code":"ﳡ","end":false},{"code":"ﳢ","end":false},{"code":"ﳣ","end":false},{"code":"ﳤ","end":true}]}],"verses":[{"key":"45:1","surah":45,"ayah":1,"num":4474,"page":499,"words":[{"code":"ﱁ","page":499,"end":false},{"code":"ﱂ","page":499,"end":true}],"text":"حمٓ"},{"key":"45:2","surah":45,"ayah":2,"num":4475,"page":499,"words":[{"code":"ﱃ","page":499,"end":false},{"code":"ﱄ","page":499,"end":false},{"code":"ﱅ","page":499,"end":false},{"code":"ﱆ","page":499,"end":false},{"code":"ﱇ","page":499,"end":false},{"code":"ﱈ","page":499,"end":false},{"code":"ﱉ","page":499,"end":true}],"text":"تَنزِيلُ ٱلْكِتَـٰبِ مِنَ ٱللَّهِ ٱلْعَزِيزِ ٱلْحَكِيمِ"},{"key":"45:3","surah":45,"ayah":3,"num":4476,"page":499,"words":[{"code":"ﱊ","page":499,"end":false},{"code":"ﱋ","page":499,"end":false},{"code":"ﱌ","page":499,"end":false},{"code":"ﱍ","page":499,"end":false},{"code":"ﱎ","page":499,"end":false},{"code":"ﱏ","page":499,"end":false},{"code":"ﱐ","page":499,"end":true}],"text":"إِنَّ فِى ٱلسَّمَـٰوَٰتِ وَٱلْأَرْضِ لَـَٔايَـٰتٍۢ لِّلْمُؤْمِنِينَ"},{"key":"45:4","surah":45,"ayah":4,"num":4477,"page":499,"words":[{"code":"ﱑ","page":499,"end":false},{"code":"ﱒ","page":499,"end":false},{"code":"ﱓ","page":499,"end":false},{"code":"ﱔ","page":499,"end":false},{"code":"ﱕ","page":499,"end":false},{"code":"ﱖ","page":499,"end":false},{"code":"ﱗ","page":499,"end":false},{"code":"ﱘ","page":499,"end":false},{"code":"ﱙ","page":499,"end":false},{"code":"ﱚ","page":499,"end":true}],"text":"وَفِى خَلْقِكُمْ وَمَا يَبُثُّ مِن دَآبَّةٍ ءَايَـٰتٌۭ لِّقَوْمٍۢ يُوقِنُونَ"},{"key":"45:5","surah":45,"ayah":5,"num":4478,"page":499,"words":[{"code":"ﱛ","page":499,"end":false},{"code":"ﱜ","page":499,"end":false},{"code":"ﱝ","page":499,"end":false},{"code":"ﱞ","page":499,"end":false},{"code":"ﱟ","page":499,"end":false},{"code":"ﱠ","page":499,"end":false},{"code":"ﱡ","page":499,"end":false},{"code":"ﱢ","page":499,"end":false},{"code":"ﱣ","page":499,"end":false},{"code":"ﱤ","page":499,"end":false},{"code":"ﱥ","page":499,"end":false},{"code":"ﱦ","page":499,"end":false},{"code":"ﱧ","page":499,"end":false},{"code":"ﱨ","page":499,"end":false},{"code":"ﱩ","page":499,"end":false},{"code":"ﱪ","page":499,"end":false},{"code":"ﱫ","page":499,"end":false},{"code":"ﱬ","page":499,"end":false},{"code":"ﱭ","page":499,"end":false},{"code":"ﱮ","page":499,"end":false},{"code":"ﱯ","page":499,"end":true}],"text":"وَٱخْتِلَـٰفِ ٱلَّيْلِ وَٱلنَّهَارِ وَمَآ أَنزَلَ ٱللَّهُ مِنَ ٱلسَّمَآءِ مِن رِّزْقٍۢ فَأَحْيَا بِهِ ٱلْأَرْضَ بَعْدَ مَوْتِهَا وَتَصْرِيفِ ٱلرِّيَـٰحِ ءَايَـٰتٌۭ لِّقَوْمٍۢ يَعْقِلُونَ"},{"key":"45:6","surah":45,"ayah":6,"num":4479,"page":499,"words":[{"code":"ﱰ","page":499,"end":false},{"code":"ﱱ","page":499,"end":false},{"code":"ﱲ","page":499,"end":false},{"code":"ﱳ","page":499,"end":false},{"code":"ﱴ","page":499,"end":false},{"code":"ﱵﱶ","page":499,"end":false},{"code":"ﱷ","page":499,"end":false},{"code":"ﱸ","page":499,"end":false},{"code":"ﱹ","page":499,"end":false},{"code":"ﱺ","page":499,"end":false},{"code":"ﱻ","page":499,"end":false},{"code":"ﱼ","page":499,"end":false},{"code":"ﱽ","page":499,"end":true}],"text":"تِلْكَ ءَايَـٰتُ ٱللَّهِ نَتْلُوهَا عَلَيْكَ بِٱلْحَقِّ ۖ فَبِأَىِّ حَدِيثٍۭ بَعْدَ ٱللَّهِ وَءَايَـٰتِهِۦ يُؤْمِنُونَ"},{"key":"45:7","surah":45,"ayah":7,"num":4480,"page":499,"words":[{"code":"ﱾ","page":499,"end":false},{"code":"ﱿ","page":499,"end":false},{"code":"ﲀ","page":499,"end":false},{"code":"ﲁ","page":499,"end":false},{"code":"ﲂ","page":499,"end":true}],"text":"وَيْلٌۭ لِّكُلِّ أَفَّاكٍ أَثِيمٍۢ"},{"key":"45:8","surah":45,"ayah":8,"num":4481,"page":499,"words":[{"code":"ﲃ","page":499,"end":false},{"code":"ﲄ","page":499,"end":false},{"code":"ﲅ","page":499,"end":false},{"code":"ﲆ","page":499,"end":false},{"code":"ﲇ","page":499,"end":false},{"code":"ﲈ","page":499,"end":false},{"code":"ﲉ","page":499,"end":false},{"code":"ﲊ","page":499,"end":false},{"code":"ﲋ","page":499,"end":false},{"code":"ﲌ","page":499,"end":false},{"code":"ﲍﲎ","page":499,"end":false},{"code":"ﲏ","page":499,"end":false},{"code":"ﲐ","page":499,"end":false},{"code":"ﲑ","page":499,"end":false},{"code":"ﲒ","page":499,"end":true}],"text":"يَسْمَعُ ءَايَـٰتِ ٱللَّهِ تُتْلَىٰ عَلَيْهِ ثُمَّ يُصِرُّ مُسْتَكْبِرًۭا كَأَن لَّمْ يَسْمَعْهَا ۖ فَبَشِّرْهُ بِعَذَابٍ أَلِيمٍۢ"},{"key":"45:9","surah":45,"ayah":9,"num":4482,"page":499,"words":[{"code":"ﲓ","page":499,"end":false},{"code":"ﲔ","page":499,"end":false},{"code":"ﲕ","page":499,"end":false},{"code":"ﲖ","page":499,"end":false},{"code":"ﲗ","page":499,"end":false},{"code":"ﲘ","page":499,"end":false},{"code":"ﲙﲚ","page":499,"end":false},{"code":"ﲛ","page":499,"end":false},{"code":"ﲜ","page":499,"end":false},{"code":"ﲝ","page":499,"end":false},{"code":"ﲞ","page":499,"end":false},{"code":"ﲟ","page":499,"end":true}],"text":"وَإِذَا عَلِمَ مِنْ ءَايَـٰتِنَا شَيْـًٔا ٱتَّخَذَهَا هُزُوًا ۚ أُو۟لَـٰٓئِكَ لَهُمْ عَذَابٌۭ مُّهِينٌۭ"},{"key":"45:10","surah":45,"ayah":10,"num":4483,"page":499,"words":[{"code":"ﲠ","page":499,"end":false},{"code":"ﲡ","page":499,"end":false},{"code":"ﲢﲣ","page":499,"end":false},{"code":"ﲤ","page":499,"end":false},{"code":"ﲥ","page":499,"end":false},{"code":"ﲦ","page":499,"end":false},{"code":"ﲧ","page":499,"end":false},{"code":"ﲨ","page":499,"end":false},{"code":"ﲩ","page":499,"end":false},{"code":"ﲪ","page":499,"end":false},{"code":"ﲫ","page":499,"end":false},{"code":"ﲬ","page":499,"end":false},{"code":"ﲭ","page":499,"end":false},{"code":"ﲮ","page":499,"end":false},{"code":"ﲯ","page":499,"end":false},{"code":"ﲰﲱ","page":499,"end":false},{"code":"ﲲ","page":499,"end":false},{"code":"ﲳ","page":499,"end":false},{"code":"ﲴ","page":499,"end":false},{"code":"ﲵ","page":499,"end":true}],"text":"مِّن وَرَآئِهِمْ جَهَنَّمُ ۖ وَلَا يُغْنِى عَنْهُم مَّا كَسَبُوا۟ شَيْـًۭٔا وَلَا مَا ٱتَّخَذُوا۟ مِن دُونِ ٱللَّهِ أَوْلِيَآءَ ۖ وَلَهُمْ عَذَابٌ عَظِيمٌ"},{"key":"45:11","surah":45,"ayah":11,"num":4484,"page":499,"words":[{"code":"ﲶ","page":499,"end":false},{"code":"ﲷﲸ","page":499,"end":false},{"code":"ﲹ","page":499,"end":false},{"code":"ﲺ","page":499,"end":false},{"code":"ﲻ","page":499,"end":false},{"code":"ﲼ","page":499,"end":false},{"code":"ﲽ","page":499,"end":false},{"code":"ﲾ","page":499,"end":false},{"code":"ﲿ","page":499,"end":false},{"code":"ﳀ","page":499,"end":false},{"code":"ﳁ","page":499,"end":false},{"code":"ﳂ","page":499,"end":true}],"text":"هَـٰذَا هُدًۭى ۖ وَٱلَّذِينَ كَفَرُوا۟ بِـَٔايَـٰتِ رَبِّهِمْ لَهُمْ عَذَابٌۭ مِّن رِّجْزٍ أَلِيمٌ"},{"key":"45:12","surah":45,"ayah":12,"num":4485,"page":499,"words":[{"code":"ﳃ ﳄ","page":499,"end":false},{"code":"ﳅ","page":499,"end":false},{"code":"ﳆ","page":499,"end":false},{"code":"ﳇ","page":499,"end":false},{"code":"ﳈ","page":499,"end":false},{"code":"ﳉ","page":499,"end":false},{"code":"ﳊ","page":499,"end":false},{"code":"ﳋ","page":499,"end":false},{"code":"ﳌ","page":499,"end":false},{"code":"ﳍ","page":499,"end":false},{"code":"ﳎ","page":499,"end":false},{"code":"ﳏ","page":499,"end":false},{"code":"ﳐ","page":499,"end":false},{"code":"ﳑ","page":499,"end":false},{"code":"ﳒ","page":499,"end":true}],"text":"۞ ٱللَّهُ ٱلَّذِى سَخَّرَ لَكُمُ ٱلْبَحْرَ لِتَجْرِىَ ٱلْفُلْكُ فِيهِ بِأَمْرِهِۦ وَلِتَبْتَغُوا۟ مِن فَضْلِهِۦ وَلَعَلَّكُمْ تَشْكُرُونَ"},{"key":"45:13","surah":45,"ayah":13,"num":4486,"page":499,"words":[{"code":"ﳓ","page":499,"end":false},{"code":"ﳔ","page":499,"end":false},{"code":"ﳕ","page":499,"end":false},{"code":"ﳖ","page":499,"end":false},{"code":"ﳗ","page":499,"end":false},{"code":"ﳘ","page":499,"end":false},{"code":"ﳙ","page":499,"end":false},{"code":"ﳚ","page":499,"end":false},{"code":"ﳛ","page":499,"end":false},{"code":"ﳜﳝ","page":499,"end":false},{"code":"ﳞ","page":499,"end":false},{"code":"ﳟ","page":499,"end":false},{"code":"ﳠ","page":499,"end":false},{"code":"ﳡ","page":499,"end":false},{"code":"ﳢ","page":499,"end":false},{"code":"ﳣ","page":499,"end":false},{"code":"ﳤ","page":499,"end":true}],"text":"وَسَخَّرَ لَكُم مَّا فِى ٱلسَّمَـٰوَٰتِ وَمَا فِى ٱلْأَرْضِ جَمِيعًۭا مِّنْهُ ۚ إِنَّ فِى ذَٰلِكَ لَـَٔايَـٰتٍۢ لِّقَوْمٍۢ يَتَفَكَّرُونَ"}]}