{"page":537,"lines":[{"lineNumber":1,"words":[{"code":"ﱁ","end":false},{"code":"ﱂ","end":false},{"code":"ﱃ","end":false},{"code":"ﱄ","end":true},{"code":"ﱅ","end":false},{"code":"ﱆ","end":false},{"code":"ﱇ","end":false},{"code":"ﱈ","end":true},{"code":"ﱉ","end":false},{"code":"ﱊ","end":false},{"code":"ﱋ","end":false}]},{"lineNumber":2,"words":[{"code":"ﱌ","end":false},{"code":"ﱍ","end":true},{"code":"ﱎ","end":false},{"code":"ﱏ","end":false},{"code":"ﱐ","end":false},{"code":"ﱑ","end":false},{"code":"ﱒ","end":true},{"code":"ﱓ","end":false},{"code":"ﱔ","end":false}]},{"lineNumber":3,"words":[{"code":"ﱕ","end":false},{"code":"ﱖ","end":false},{"code":"ﱗ","end":true},{"code":"ﱘ","end":false},{"code":"ﱙ","end":false},{"code":"ﱚ","end":false},{"code":"ﱛ","end":false},{"code":"ﱜ","end":true},{"code":"ﱝ","end":false}]},{"lineNumber":4,"words":[{"code":"ﱞ","end":false},{"code":"ﱟ","end":false},{"code":"ﱠ","end":false},{"code":"ﱡ","end":true},{"code":"ﱢ","end":false},{"code":"ﱣ","end":false},{"code":"ﱤ","end":false},{"code":"ﱥ","end":true},{"code":"ﱦ","end":false},{"code":"ﱧ","end":false}]},{"lineNumber":5,"words":[{"code":"ﱨ","end":false},{"code":"ﱩ","end":false},{"code":"ﱪ","end":false},{"code":"ﱫ","end":false},{"code":"ﱬ","end":false},{"code":"ﱭ","end":true},{"code":"ﱮ","end":false},{"code":"ﱯ","end":false},{"code":"ﱰ","end":false},{"code":"ﱱ","end":false},{"code":"ﱲ","end":false}]},{"lineNumber":6,"words":[{"code":"ﱳ","end":true},{"code":"ﱴ","end":false},{"code":"ﱵ","end":false},{"code":"ﱶ","end":false},{"code":"ﱷ","end":false},{"code":"ﱸ","end":true},{"code":"ﱹ","end":false},{"code":"ﱺ","end":false},{"code":"ﱻ","end":false},{"code":"ﱼ","end":false},{"code":"ﱽ","end":false}]},{"lineNumber":7,"words":[{"code":"ﱾ","end":true},{"code":"ﱿ","end":false},{"code":"ﲀ","end":false},{"code":"ﲁ","end":false},{"code":"ﲂ","end":false},{"code":"ﲃ","end":true},{"code":"ﲄ","end":false},{"code":"ﲅ","end":false},{"code":"ﲆ","end":false},{"code":"ﲇ","end":false},{"code":"ﲈ","end":false}]},{"lineNumber":8,"words":[{"code":"ﲉ","end":false},{"code":"ﲊ","end":true},{"code":"ﲋ","end":false},{"code":"ﲌ","end":false},{"code":"ﲍ","end":false},{"code":"ﲎ","end":false},{"code":"ﲏ","end":false},{"code":"ﲐ","end":true},{"code":"ﲑ","end":false},{"code":"ﲒ","end":false},{"code":"ﲓ","end":false},{"code":"ﲔ","end":false}]},{"lineNumber":9,"words":[{"code":"ﲕ","end":false},{"code":"ﲖ","end":false},{"code":"ﲗ","end":true},{"code":"ﲘ","end":false},{"code":"ﲙ","end":false},{"code":"ﲚ","end":false},{"code":"ﲛ","end":true},{"code":"ﲜ","end":false},{"code":"ﲝ","end":false}]},{"lineNumber":10,"words":[{"code":"ﲞ","end":true},{"code":"ﲟ","end":false},{"code":"ﲠ","end":false},{"code":"ﲡ","end":false},{"code":"ﲢ","end":false},{"code":"ﲣ","end":false},{"code":"ﲤ","end":true},{"code":"ﲥ","end":false},{"code":"ﲦ","end":false},{"code":"ﲧ","end":false},{"code":"ﲨ","end":false},{"code":"ﲩ","end":true}]},{"lineNumber":13,"words":[{"code":"ﲪ","end":false},{"code":"ﲫ","end":false},{"code":"ﲬ","end":false},{"code":"ﲭ","end":false},{"code":"ﲮ","end":false},{"code":"ﲯﲰ","end":false},{"code":"ﲱ","end":false},{"code":"ﲲ","end":false},{"code":"ﲳ","end":false},{"code":"ﲴ","end":true},{"code":"ﲵ","end":false},{"code":"ﲶ","end":false}]},{"lineNumber":14,"words":[{"code":"ﲷ","end":false},{"code":"ﲸﲹ","end":false},{"code":"ﲺ","end":false},{"code":"ﲻﲼ","end":false},{"code":"ﲽ","end":false},{"code":"ﲾ","end":false},{"code":"ﲿ","end":false},{"code":"ﳀ","end":false},{"code":"ﳁ","end":false},{"code":"ﳂ","end":true},{"code":"ﳃ","end":false}]},{"lineNumber":15,"words":[{"code":"ﳄ","end":false},{"code":"ﳅ","end":false},{"code":"ﳆ","end":false},{"code":"ﳇﳈ","end":false},{"code":"ﳉ","end":false},{"code":"ﳊ","end":false},{"code":"ﳋ","end":false},{"code":"ﳌ","end":false},{"code":"ﳍ","end":true}]}],"verses":[{"key":"56:77","surah":56,"ayah":77,"num":5056,"page":537,"words":[{"code":"ﱁ","page":537,"end":false},{"code":"ﱂ","page":537,"end":false},{"code":"ﱃ","page":537,"end":false},{"code":"ﱄ","page":537,"end":true}],"text":"إِنَّهُۥ لَقُرْءَانٌۭ كَرِيمٌۭ"},{"key":"56:78","surah":56,"ayah":78,"num":5057,"page":537,"words":[{"code":"ﱅ","page":537,"end":false},{"code":"ﱆ","page":537,"end":false},{"code":"ﱇ","page":537,"end":false},{"code":"ﱈ","page":537,"end":true}],"text":"فِى كِتَـٰبٍۢ مَّكْنُونٍۢ"},{"key":"56:79","surah":56,"ayah":79,"num":5058,"page":537,"words":[{"code":"ﱉ","page":537,"end":false},{"code":"ﱊ","page":537,"end":false},{"code":"ﱋ","page":537,"end":false},{"code":"ﱌ","page":537,"end":false},{"code":"ﱍ","page":537,"end":true}],"text":"لَّا يَمَسُّهُۥٓ إِلَّا ٱلْمُطَهَّرُونَ"},{"key":"56:80","surah":56,"ayah":80,"num":5059,"page":537,"words":[{"code":"ﱎ","page":537,"end":false},{"code":"ﱏ","page":537,"end":false},{"code":"ﱐ","page":537,"end":false},{"code":"ﱑ","page":537,"end":false},{"code":"ﱒ","page":537,"end":true}],"text":"تَنزِيلٌۭ مِّن رَّبِّ ٱلْعَـٰلَمِينَ"},{"key":"56:81","surah":56,"ayah":81,"num":5060,"page":537,"words":[{"code":"ﱓ","page":537,"end":false},{"code":"ﱔ","page":537,"end":false},{"code":"ﱕ","page":537,"end":false},{"code":"ﱖ","page":537,"end":false},{"code":"ﱗ","page":537,"end":true}],"text":"أَفَبِهَـٰذَا ٱلْحَدِيثِ أَنتُم مُّدْهِنُونَ"},{"key":"56:82","surah":56,"ayah":82,"num":5061,"page":537,"words":[{"code":"ﱘ","page":537,"end":false},{"code":"ﱙ","page":537,"end":false},{"code":"ﱚ","page":537,"end":false},{"code":"ﱛ","page":537,"end":false},{"code":"ﱜ","page":537,"end":true}],"text":"وَتَجْعَلُونَ رِزْقَكُمْ أَنَّكُمْ تُكَذِّبُونَ"},{"key":"56:83","surah":56,"ayah":83,"num":5062,"page":537,"words":[{"code":"ﱝ","page":537,"end":false},{"code":"ﱞ","page":537,"end":false},{"code":"ﱟ","page":537,"end":false},{"code":"ﱠ","page":537,"end":false},{"code":"ﱡ","page":537,"end":true}],"text":"فَلَوْلَآ إِذَا بَلَغَتِ ٱلْحُلْقُومَ"},{"key":"56:84","surah":56,"ayah":84,"num":5063,"page":537,"words":[{"code":"ﱢ","page":537,"end":false},{"code":"ﱣ","page":537,"end":false},{"code":"ﱤ","page":537,"end":false},{"code":"ﱥ","page":537,"end":true}],"text":"وَأَنتُمْ حِينَئِذٍۢ تَنظُرُونَ"},{"key":"56:85","surah":56,"ayah":85,"num":5064,"page":537,"words":[{"code":"ﱦ","page":537,"end":false},{"code":"ﱧ","page":537,"end":false},{"code":"ﱨ","page":537,"end":false},{"code":"ﱩ","page":537,"end":false},{"code":"ﱪ","page":537,"end":false},{"code":"ﱫ","page":537,"end":false},{"code":"ﱬ","page":537,"end":false},{"code":"ﱭ","page":537,"end":true}],"text":"وَنَحْنُ أَقْرَبُ إِلَيْهِ مِنكُمْ وَلَـٰكِن لَّا تُبْصِرُونَ"},{"key":"56:86","surah":56,"ayah":86,"num":5065,"page":537,"words":[{"code":"ﱮ","page":537,"end":false},{"code":"ﱯ","page":537,"end":false},{"code":"ﱰ","page":537,"end":false},{"code":"ﱱ","page":537,"end":false},{"code":"ﱲ","page":537,"end":false},{"code":"ﱳ","page":537,"end":true}],"text":"فَلَوْلَآ إِن كُنتُمْ غَيْرَ مَدِينِينَ"},{"key":"56:87","surah":56,"ayah":87,"num":5066,"page":537,"words":[{"code":"ﱴ","page":537,"end":false},{"code":"ﱵ","page":537,"end":false},{"code":"ﱶ","page":537,"end":false},{"code":"ﱷ","page":537,"end":false},{"code":"ﱸ","page":537,"end":true}],"text":"تَرْجِعُونَهَآ إِن كُنتُمْ صَـٰدِقِينَ"},{"key":"56:88","surah":56,"ayah":88,"num":5067,"page":537,"words":[{"code":"ﱹ","page":537,"end":false},{"code":"ﱺ","page":537,"end":false},{"code":"ﱻ","page":537,"end":false},{"code":"ﱼ","page":537,"end":false},{"code":"ﱽ","page":537,"end":false},{"code":"ﱾ","page":537,"end":true}],"text":"فَأَمَّآ إِن كَانَ مِنَ ٱلْمُقَرَّبِينَ"},{"key":"56:89","surah":56,"ayah":89,"num":5068,"page":537,"words":[{"code":"ﱿ","page":537,"end":false},{"code":"ﲀ","page":537,"end":false},{"code":"ﲁ","page":537,"end":false},{"code":"ﲂ","page":537,"end":false},{"code":"ﲃ","page":537,"end":true}],"text":"فَرَوْحٌۭ وَرَيْحَانٌۭ وَجَنَّتُ نَعِيمٍۢ"},{"key":"56:90","surah":56,"ayah":90,"num":5069,"page":537,"words":[{"code":"ﲄ","page":537,"end":false},{"code":"ﲅ","page":537,"end":false},{"code":"ﲆ","page":537,"end":false},{"code":"ﲇ","page":537,"end":false},{"code":"ﲈ","page":537,"end":false},{"code":"ﲉ","page":537,"end":false},{"code":"ﲊ","page":537,"end":true}],"text":"وَأَمَّآ إِن كَانَ مِنْ أَصْحَـٰبِ ٱلْيَمِينِ"},{"key":"56:91","surah":56,"ayah":91,"num":5070,"page":537,"words":[{"code":"ﲋ","page":537,"end":false},{"code":"ﲌ","page":537,"end":false},{"code":"ﲍ","page":537,"end":false},{"code":"ﲎ","page":537,"end":false},{"code":"ﲏ","page":537,"end":false},{"code":"ﲐ","page":537,"end":true}],"text":"فَسَلَـٰمٌۭ لَّكَ مِنْ أَصْحَـٰبِ ٱلْيَمِينِ"},{"key":"56:92","surah":56,"ayah":92,"num":5071,"page":537,"words":[{"code":"ﲑ","page":537,"end":false},{"code":"ﲒ","page":537,"end":false},{"code":"ﲓ","page":537,"end":false},{"code":"ﲔ","page":537,"end":false},{"code":"ﲕ","page":537,"end":false},{"code":"ﲖ","page":537,"end":false},{"code":"ﲗ","page":537,"end":true}],"text":"وَأَمَّآ إِن كَانَ مِنَ ٱلْمُكَذِّبِينَ ٱلضَّآلِّينَ"},{"key":"56:93","surah":56,"ayah":93,"num":5072,"page":537,"words":[{"code":"ﲘ","page":537,"end":false},{"code":"ﲙ","page":537,"end":false},{"code":"ﲚ","page":537,"end":false},{"code":"ﲛ","page":537,"end":true}],"text":"فَنُزُلٌۭ مِّنْ حَمِيمٍۢ"},{"key":"56:94","surah":56,"ayah":94,"num":5073,"page":537,"words":[{"code":"ﲜ","page":537,"end":false},{"code":"ﲝ","page":537,"end":false},{"code":"ﲞ","page":537,"end":true}],"text":"وَتَصْلِيَةُ جَحِيمٍ"},{"key":"56:95","surah":56,"ayah":95,"num":5074,"page":537,"words":[{"code":"ﲟ","page":537,"end":false},{"code":"ﲠ","page":537,"end":false},{"code":"ﲡ","page":537,"end":false},{"code":"ﲢ","page":537,"end":false},{"code":"ﲣ","page":537,"end":false},{"code":"ﲤ","page":537,"end":true}],"text":"إِنَّ هَـٰذَا لَهُوَ حَقُّ ٱلْيَقِينِ"},{"key":"56:96","surah":56,"ayah":96,"num":5075,"page":537,"words":[{"code":"ﲥ","page":537,"end":false},{"code":"ﲦ","page":537,"end":false},{"code":"ﲧ","page":537,"end":false},{"code":"ﲨ","page":537,"end":false},{"code":"ﲩ","page":537,"end":true}],"text":"فَسَبِّحْ بِٱسْمِ رَبِّكَ ٱلْعَظِيمِ"},{"key":"57:1","surah":57,"ayah":1,"num":5076,"page":537,"words":[{"code":"ﲪ","page":537,"end":false},{"code":"ﲫ","page":537,"end":false},{"code":"ﲬ","page":537,"end":false},{"code":"ﲭ","page":537,"end":false},{"code":"ﲮ","page":537,"end":false},{"code":"ﲯﲰ","page":537,"end":false},{"code":"ﲱ","page":537,"end":false},{"code":"ﲲ","page":537,"end":false},{"code":"ﲳ","page":537,"end":false},{"code":"ﲴ","page":537,"end":true}],"text":"سَبَّحَ لِلَّهِ مَا فِى ٱلسَّمَـٰوَٰتِ وَٱلْأَرْضِ ۖ وَهُوَ ٱلْعَزِيزُ ٱلْحَكِيمُ"},{"key":"57:2","surah":57,"ayah":2,"num":5077,"page":537,"words":[{"code":"ﲵ","page":537,"end":false},{"code":"ﲶ","page":537,"end":false},{"code":"ﲷ","page":537,"end":false},{"code":"ﲸﲹ","page":537,"end":false},{"code":"ﲺ","page":537,"end":false},{"code":"ﲻﲼ","page":537,"end":false},{"code":"ﲽ","page":537,"end":false},{"code":"ﲾ","page":537,"end":false},{"code":"ﲿ","page":537,"end":false},{"code":"ﳀ","page":537,"end":false},{"code":"ﳁ","page":537,"end":false},{"code":"ﳂ","page":537,"end":true}],"text":"لَهُۥ مُلْكُ ٱلسَّمَـٰوَٰتِ وَٱلْأَرْضِ ۖ يُحْىِۦ وَيُمِيتُ ۖ وَهُوَ عَلَىٰ كُلِّ شَىْءٍۢ قَدِيرٌ"},{"key":"57:3","surah":57,"ayah":3,"num":5078,"page":537,"words":[{"code":"ﳃ","page":537,"end":false},{"code":"ﳄ","page":537,"end":false},{"code":"ﳅ","page":537,"end":false},{"code":"ﳆ","page":537,"end":false},{"code":"ﳇﳈ","page":537,"end":false},{"code":"ﳉ","page":537,"end":false},{"code":"ﳊ","page":537,"end":false},{"code":"ﳋ","page":537,"end":false},{"code":"ﳌ","page":537,"end":false},{"code":"ﳍ","page":537,"end":true}],"text":"هُوَ ٱلْأَوَّلُ وَٱلْـَٔاخِرُ وَٱلظَّـٰهِرُ وَٱلْبَاطِنُ ۖ وَهُوَ بِكُلِّ شَىْءٍ عَلِيمٌ"}]}