{"page":602,"lines":[{"lineNumber":3,"words":[{"code":"ﱁ","end":false},{"code":"ﱂ","end":false},{"code":"ﱃ","end":true},{"code":"ﱄ","end":false},{"code":"ﱅ","end":false},{"code":"ﱆ","end":false},{"code":"ﱇ","end":false}]},{"lineNumber":4,"words":[{"code":"ﱈ","end":true},{"code":"ﱉ","end":false},{"code":"ﱊ","end":false},{"code":"ﱋ","end":false},{"code":"ﱌ","end":false},{"code":"ﱍ","end":true},{"code":"ﱎ","end":false},{"code":"ﱏ","end":false}]},{"lineNumber":5,"words":[{"code":"ﱐ","end":false},{"code":"ﱑ","end":false},{"code":"ﱒ","end":false},{"code":"ﱓ","end":false},{"code":"ﱔ","end":false},{"code":"ﱕ","end":true}]},{"lineNumber":8,"words":[{"code":"ﱖ","end":false},{"code":"ﱗ","end":false},{"code":"ﱘ","end":false},{"code":"ﱙ","end":false},{"code":"ﱚ","end":true},{"code":"ﱛ","end":false},{"code":"ﱜ","end":false},{"code":"ﱝ","end":false}]},{"lineNumber":9,"words":[{"code":"ﱞ","end":false},{"code":"ﱟ","end":true},{"code":"ﱠ","end":false},{"code":"ﱡ","end":false},{"code":"ﱢ","end":false},{"code":"ﱣ","end":false},{"code":"ﱤ","end":false},{"code":"ﱥ","end":true},{"code":"ﱦ","end":false}]},{"lineNumber":10,"words":[{"code":"ﱧ","end":false},{"code":"ﱨ","end":true},{"code":"ﱩ","end":false},{"code":"ﱪ","end":false},{"code":"ﱫ","end":false},{"code":"ﱬ","end":false},{"code":"ﱭ","end":false}]},{"lineNumber":11,"words":[{"code":"ﱮ","end":true},{"code":"ﱯ","end":false},{"code":"ﱰ","end":false},{"code":"ﱱ","end":false},{"code":"ﱲ","end":true},{"code":"ﱳ","end":false},{"code":"ﱴ","end":false},{"code":"ﱵ","end":true}]},{"lineNumber":14,"words":[{"code":"ﱶ","end":false},{"code":"ﱷ","end":false},{"code":"ﱸ","end":false},{"code":"ﱹ","end":true},{"code":"ﱺ","end":false},{"code":"ﱻ","end":false},{"code":"ﱼ","end":false},{"code":"ﱽ","end":true}]},{"lineNumber":15,"words":[{"code":"ﱾ","end":false},{"code":"ﱿ","end":false},{"code":"ﲀ","end":false},{"code":"ﲁ","end":false},{"code":"ﲂ","end":true}]}],"verses":[{"key":"106:1","surah":106,"ayah":1,"num":6194,"page":602,"words":[{"code":"ﱁ","page":602,"end":false},{"code":"ﱂ","page":602,"end":false},{"code":"ﱃ","page":602,"end":true}],"text":"لِإِيلَـٰفِ قُرَيْشٍ"},{"key":"106:2","surah":106,"ayah":2,"num":6195,"page":602,"words":[{"code":"ﱄ","page":602,"end":false},{"code":"ﱅ","page":602,"end":false},{"code":"ﱆ","page":602,"end":false},{"code":"ﱇ","page":602,"end":false},{"code":"ﱈ","page":602,"end":true}],"text":"إِۦلَـٰفِهِمْ رِحْلَةَ ٱلشِّتَآءِ وَٱلصَّيْفِ"},{"key":"106:3","surah":106,"ayah":3,"num":6196,"page":602,"words":[{"code":"ﱉ","page":602,"end":false},{"code":"ﱊ","page":602,"end":false},{"code":"ﱋ","page":602,"end":false},{"code":"ﱌ","page":602,"end":false},{"code":"ﱍ","page":602,"end":true}],"text":"فَلْيَعْبُدُوا۟ رَبَّ هَـٰذَا ٱلْبَيْتِ"},{"key":"106:4","surah":106,"ayah":4,"num":6197,"page":602,"words":[{"code":"ﱎ","page":602,"end":false},{"code":"ﱏ","page":602,"end":false},{"code":"ﱐ","page":602,"end":false},{"code":"ﱑ","page":602,"end":false},{"code":"ﱒ","page":602,"end":false},{"code":"ﱓ","page":602,"end":false},{"code":"ﱔ","page":602,"end":false},{"code":"ﱕ","page":602,"end":true}],"text":"ٱلَّذِىٓ أَطْعَمَهُم مِّن جُوعٍۢ وَءَامَنَهُم مِّنْ خَوْفٍۭ"},{"key":"107:1","surah":107,"ayah":1,"num":6198,"page":602,"words":[{"code":"ﱖ","page":602,"end":false},{"code":"ﱗ","page":602,"end":false},{"code":"ﱘ","page":602,"end":false},{"code":"ﱙ","page":602,"end":false},{"code":"ﱚ","page":602,"end":true}],"text":"أَرَءَيْتَ ٱلَّذِى يُكَذِّبُ بِٱلدِّينِ"},{"key":"107:2","surah":107,"ayah":2,"num":6199,"page":602,"words":[{"code":"ﱛ","page":602,"end":false},{"code":"ﱜ","page":602,"end":false},{"code":"ﱝ","page":602,"end":false},{"code":"ﱞ","page":602,"end":false},{"code":"ﱟ","page":602,"end":true}],"text":"فَذَٰلِكَ ٱلَّذِى يَدُعُّ ٱلْيَتِيمَ"},{"key":"107:3","surah":107,"ayah":3,"num":6200,"page":602,"words":[{"code":"ﱠ","page":602,"end":false},{"code":"ﱡ","page":602,"end":false},{"code":"ﱢ","page":602,"end":false},{"code":"ﱣ","page":602,"end":false},{"code":"ﱤ","page":602,"end":false},{"code":"ﱥ","page":602,"end":true}],"text":"وَلَا يَحُضُّ عَلَىٰ طَعَامِ ٱلْمِسْكِينِ"},{"key":"107:4","surah":107,"ayah":4,"num":6201,"page":602,"words":[{"code":"ﱦ","page":602,"end":false},{"code":"ﱧ","page":602,"end":false},{"code":"ﱨ","page":602,"end":true}],"text":"فَوَيْلٌۭ لِّلْمُصَلِّينَ"},{"key":"107:5","surah":107,"ayah":5,"num":6202,"page":602,"words":[{"code":"ﱩ","page":602,"end":false},{"code":"ﱪ","page":602,"end":false},{"code":"ﱫ","page":602,"end":false},{"code":"ﱬ","page":602,"end":false},{"code":"ﱭ","page":602,"end":false},{"code":"ﱮ","page":602,"end":true}],"text":"ٱلَّذِينَ هُمْ عَن صَلَاتِهِمْ سَاهُونَ"},{"key":"107:6","surah":107,"ayah":6,"num":6203,"page":602,"words":[{"code":"ﱯ","page":602,"end":false},{"code":"ﱰ","page":602,"end":false},{"code":"ﱱ","page":602,"end":false},{"code":"ﱲ","page":602,"end":true}],"text":"ٱلَّذِينَ هُمْ يُرَآءُونَ"},{"key":"107:7","surah":107,"ayah":7,"num":6204,"page":602,"words":[{"code":"ﱳ","page":602,"end":false},{"code":"ﱴ","page":602,"end":false},{"code":"ﱵ","page":602,"end":true}],"text":"وَيَمْنَعُونَ ٱلْمَاعُونَ"},{"key":"108:1","surah":108,"ayah":1,"num":6205,"page":602,"words":[{"code":"ﱶ","page":602,"end":false},{"code":"ﱷ","page":602,"end":false},{"code":"ﱸ","page":602,"end":false},{"code":"ﱹ","page":602,"end":true}],"text":"إِنَّآ أَعْطَيْنَـٰكَ ٱلْكَوْثَرَ"},{"key":"108:2","surah":108,"ayah":2,"num":6206,"page":602,"words":[{"code":"ﱺ","page":602,"end":false},{"code":"ﱻ","page":602,"end":false},{"code":"ﱼ","page":602,"end":false},{"code":"ﱽ","page":602,"end":true}],"text":"فَصَلِّ لِرَبِّكَ وَٱنْحَرْ"},{"key":"108:3","surah":108,"ayah":3,"num":6207,"page":602,"words":[{"code":"ﱾ","page":602,"end":false},{"code":"ﱿ","page":602,"end":false},{"code":"ﲀ","page":602,"end":false},{"code":"ﲁ","page":602,"end":false},{"code":"ﲂ","page":602,"end":true}],"text":"إِنَّ شَانِئَكَ هُوَ ٱلْأَبْتَرُ"}]}